onnxruntime/ThirdPartyNotices.txt
onnxruntime/__init__.py
onnxruntime/LICENSE
onnxruntime/Privacy.md
onnxruntime/datasets/logreg_iris.onnx
onnxruntime/datasets/mul_1.onnx
onnxruntime/datasets/__init__.py
onnxruntime/datasets/sigmoid.onnx
onnxruntime/quantization/base_quantizer.py
onnxruntime/quantization/registry.py
onnxruntime/quantization/qdq_loss_debug.py
onnxruntime/quantization/preprocess.py
onnxruntime/quantization/__init__.py
onnxruntime/quantization/quant_utils.py
onnxruntime/quantization/tensor_quant_overrides.py
onnxruntime/quantization/matmul_bnb4_quantizer.py
onnxruntime/quantization/onnx_model.py
onnxruntime/quantization/matmul_4bits_quantizer.py
onnxruntime/quantization/qdq_quantizer.py
onnxruntime/quantization/shape_inference.py
onnxruntime/quantization/calibrate.py
onnxruntime/quantization/onnx_quantizer.py
onnxruntime/quantization/quantize.py
onnxruntime/quantization/CalTableFlatBuffers/__init__.py
onnxruntime/quantization/CalTableFlatBuffers/TrtTable.py
onnxruntime/quantization/CalTableFlatBuffers/KeyValue.py
onnxruntime/quantization/execution_providers/qnn/fusion_lpnorm.py
onnxruntime/quantization/execution_providers/qnn/mixed_precision_overrides_utils.py
onnxruntime/quantization/execution_providers/qnn/preprocess.py
onnxruntime/quantization/execution_providers/qnn/__init__.py
onnxruntime/quantization/execution_providers/qnn/quant_config.py
onnxruntime/quantization/operators/norm.py
onnxruntime/quantization/operators/pooling.py
onnxruntime/quantization/operators/embed_layernorm.py
onnxruntime/quantization/operators/attention.py
onnxruntime/quantization/operators/direct_q8.py
onnxruntime/quantization/operators/pad.py
onnxruntime/quantization/operators/split.py
onnxruntime/quantization/operators/gavgpool.py
onnxruntime/quantization/operators/matmul.py
onnxruntime/quantization/operators/resize.py
onnxruntime/quantization/operators/base_operator.py
onnxruntime/quantization/operators/__init__.py
onnxruntime_training_cpu-1.19.2.dist-info/top_level.txt
onnxruntime_training_cpu-1.19.2.dist-info/entry_points.txt
onnxruntime_training_cpu-1.19.2.dist-info/METADATA
onnxruntime_training_cpu-1.19.2.dist-info/WHEEL
onnxruntime_training_cpu-1.19.2.dist-info/RECORD
